oloren/__init__.py
oloren/client.py
oloren/functions.py
oloren/server.py
oloren/types.py
oloren/util.py
oloren/static/23.js
oloren/static/422.js
oloren/static/422.js.LICENSE.txt
oloren/static/438.js
oloren/static/438.js.LICENSE.txt
oloren/static/728.js
oloren/static/871.js
oloren/static/959.js
oloren/static/959.js.LICENSE.txt
oloren/static/991.js
oloren/static/991.js.LICENSE.txt
oloren/static/directory
oloren/static/index.html
oloren/static/main.js
oloren/static/remoteEntry.js
oloren/static/src_bootstrap_tsx.js
oloren/static/src_nodes_BaseNode_tsx.js
oloren/static/vendors-node_modules_pnpm_ant-design_icons_5_0_1_biqbaboplfbrettd7655fr4n2y_node_modules_ant--04b204.js
oloren/static/vendors-node_modules_pnpm_ant-design_icons_5_0_1_biqbaboplfbrettd7655fr4n2y_node_modules_ant--51e63d.js
oloren/static/vendors-node_modules_pnpm_react-dom_18_2_0_react_18_2_0_node_modules_react-dom_index_js.js
oloren/static/vendors-node_modules_pnpm_react_18_2_0_node_modules_react_index_js.js
oloren-0.0.59.dist-info/METADATA
oloren-0.0.59.dist-info/WHEEL
oloren-0.0.59.dist-info/top_level.txt
oloren-0.0.59.dist-info/RECORD
