Metadata-Version: 2.1
Name: oloren
Version: 0.0.59
Summary: A simple python library for creating Oloren Orchestrator extensions.
License: UNKNOWN
Project-URL: Docs, https://oloren-ai.github.io/python-extension-lib
Project-URL: Github, https://github.com/Oloren-AI/python-extension-lib
Project-URL: Oloren AI, https://oloren.ai
Platform: UNKNOWN
Classifier: Development Status :: 3 - Alpha
Classifier: License :: OSI Approved :: MIT License
Classifier: Programming Language :: Python :: 3
Classifier: Programming Language :: Python :: 3.6
Classifier: Programming Language :: Python :: 3.7
Classifier: Programming Language :: Python :: 3.8
Classifier: Programming Language :: Python :: 3.9
Requires-Python: >=3.6
Requires-Dist: flask
Requires-Dist: flask-cors
Requires-Dist: python-socketio
Requires-Dist: requests
